[
    {
        "first-heard-survey": "Talk TiddlyWiki",
        "other-survey-source": "",
        "are-you-a-dev": "No, I would not",
        "first-used-tw": "2012",
        "joined-tw-community": "Yes",
        "started-tw-community": "2025",
        "use-ttw": "I read and post in this community",
        "use-mailing-list": "I read/lurk, but do not post",
        "use-reddit": "I read/lurk, but do not post",
        "use-discord": "I do not engage with this community",
        "use-github-discuss": "I do not engage with this community",
        "published-plugin": "No",
        "main-use-cases": "Note-taking;As a knowledge base (including technical, non-fiction and encyclopaedic content)",
        "other-use-cases": "",
        "use-for-work-or-study": "Not applicable (as retired, etc)",
        "share-wikis": "No, my TiddlyWiki is for personal use only",
        "publish-to-web": "",
        "publish-to-intranet": "",
        "value-of-tw": "The way TW stores the data in one HTML-file. \n(I personaly use one sub-folder for media storage).",
        "tw-ability-level": "I have customised TiddlyWiki through options and plugins",
        "save-method": "Single-file wiki with TiddlyDesktop",
        "backup-method": "Web or cloud hosting (other than TiddlyHost/TiddlySpot e.g. Netlify, AWS, OVH, Google Cloud...)",
        "diy-backup-info": "",
        "wiki-setup-info": "",
        "tw-customisations": "",
        "positive-about-future": "Yes",
        "tw-future-confidence": "Yes",
        "project-decision-trust": "Yes",
        "project-strengths": "Appealing to me is that the software (application) is future proof.",
        "project-weaknesses": "I think that TW will always keeps my interest.",
        "ok-to-publish": "Yes, I am happy for my responses to be published",
        "title": "Community Survey 2025 Answer 00179",
        "tags": "[[Community Survey 2025]]"
    }
]